aptamerforge/__init__.py
aptamerforge/aptamerforge.py
aptamerforge-0.1.7.2.dist-info/licenses/LICENSE
aptamerforge-0.1.7.2.dist-info/METADATA
aptamerforge-0.1.7.2.dist-info/WHEEL
aptamerforge-0.1.7.2.dist-info/top_level.txt
aptamerforge-0.1.7.2.dist-info/RECORD
