Metadata-Version: 2.4
Name: aptamerforge
Version: 0.1.7.2
Summary: A DNA aptamer screening tool for mismatch analysis and hairpin detection & drawing
Home-page: https://github.com/Feicheiel/aptamerforge
Author: William Asamoah
Author-email: cephaswills@gmail.com
Classifier: Programming Language :: Python :: 3
Classifier: License :: OSI Approved :: MIT License
Classifier: Operating System :: OS Independent
Requires-Python: >=3.7
License-File: LICENSE
Requires-Dist: pandas
Requires-Dist: viennarna
Requires-Dist: pycairo>=1.20.0b
Dynamic: author
Dynamic: author-email
Dynamic: classifier
Dynamic: description
Dynamic: description-content-type
Dynamic: home-page
Dynamic: license-file
Dynamic: requires-dist
Dynamic: requires-python
Dynamic: summary
